rpi_inky_layout/__init__.py
rpi_inky_layout/index_order.py
rpi_inky_layout/layout.py
rpi_inky_layout/position.py
rpi_inky_layout/rotation.py
test/__init__.py
test/layout_fixtures.py
test/test_index_order.py
test/test_issue_37.py
test/test_layout_alternatePackingMode.py
test/test_layout_basics.py
test/test_layout_noLayers.py
test/test_layout_packingBias.py
test/test_layout_rotation.py
test/test_layout_vertical_packing.py
test/test_position.py
rpi_inky_layout-0.3.0.dist-info/LICENSE.txt
rpi_inky_layout-0.3.0.dist-info/METADATA
rpi_inky_layout-0.3.0.dist-info/WHEEL
rpi_inky_layout-0.3.0.dist-info/top_level.txt
rpi_inky_layout-0.3.0.dist-info/RECORD
