Metadata-Version: 2.1
Name: rpi-inky-layout
Version: 0.3.0
Summary: A layout companion library for Pimoroni's Inky HATs
Home-page: https://github.com/DoctorU/rpi-inky-layout
Author: Stephen Hobdell
Author-email: doctoruseful@gmail.com
License: MIT
Download-URL: https://github.com/DoctorU/rpi-inky-layout/dist/v0.3.0.tar.gz
Keywords: Layout,Framework,Image,Inky,Pimoroni
Platform: UNKNOWN
Classifier: Development Status :: 3 - Alpha
Classifier: Intended Audience :: Developers
Classifier: Topic :: Software Development :: Libraries :: Application Frameworks
Classifier: Topic :: Software Development :: Libraries :: Python Modules
Classifier: Topic :: Multimedia :: Graphics :: Presentation
Classifier: License :: OSI Approved :: MIT License
Classifier: Programming Language :: Python :: 3
Classifier: Programming Language :: Python :: 3.6
Classifier: Programming Language :: Python :: 3.7
Classifier: Programming Language :: Python :: 3.8
Classifier: Programming Language :: Python :: 3.9
Classifier: License :: OSI Approved :: MIT License
Classifier: Operating System :: Other OS
Requires-Dist: numpy (>=1.19.5)
Requires-Dist: Pillow (>=8.1.0)
